poocr/__init__.py
poocr/api/__init__.py
poocr/api/ocr.py
poocr/api/ocr2excel.py
poocr/core/BaiduOCR.py
poocr/core/HuaweiOCR.py
poocr/core/OCR.py
poocr/core/OfdOCR.py
poocr/core/__init__.py
poocr/lib/CommonUtils.py
poocr/lib/Config.py
poocr/lib/Const.py
poocr/lib/__init__.py
poocr/lib/apig_sdk/__init__.py
poocr/lib/apig_sdk/signer.py
tests/__init__.py
tests/test_code/__init__.py
tests/test_code/test_bugs.py
tests/test_code/test_init.py
tests/test_code/test_ocr.py
tests/test_code/test_ocr2excel.py
poocr-1.0.6.dist-info/LICENSE
poocr-1.0.6.dist-info/METADATA
poocr-1.0.6.dist-info/WHEEL
poocr-1.0.6.dist-info/top_level.txt
poocr-1.0.6.dist-info/RECORD
