Metadata-Version: 2.1
Name: poocr
Version: 1.0.6
Summary: pip install poocr
Home-page: https://www.python-office.com/
Author: CoderWanFeng
Author-email: 1957875073@qq.com
License: MIT
Project-URL: Bug Tracker, https://github.com/CoderWanFeng/poocr/issues
Project-URL: Documentation, https://github.com/CoderWanFeng/poocr/blob/main/README.md
Project-URL: Source Code, https://github.com/CoderWanFeng/poocr
Platform: any
Requires-Python: >=3.7
License-File: LICENSE
Requires-Dist: potx-cloud ==0.0.7
Requires-Dist: loguru
